README.rst
setup.cfg
setup.py
src/naming_utils/__init__.py
src/naming_utils.egg-info/PKG-INFO
src/naming_utils.egg-info/SOURCES.txt
src/naming_utils.egg-info/dependency_links.txt
src/naming_utils.egg-info/top_level.txt