Metadata-Version: 1.2
Name: naming-utils
Version: 0.0.1
Summary: Simple utility for generating unique names with timestamps.
Home-page: https://github.com/maransowthri/naming-utils.git
Author: Maran Sowthri Kalailingam
Author-email: contact@maransowthri.dev
License: MIT
Project-URL: Source, https://github.com/maransowthri/naming-utils.git
Keywords: naming, automation, log, files, utils
Platform: UNKNOWN
